setup.py
puppetdb/__init__.py
puppetdb/core.py
puppetdb/utils.py
puppetdb/v2.py
puppetdb.egg-info/PKG-INFO
puppetdb.egg-info/SOURCES.txt
puppetdb.egg-info/dependency_links.txt
puppetdb.egg-info/requires.txt
puppetdb.egg-info/top_level.txt