Metadata-Version: 1.1
Name: puppetdb
Version: 0.0.1
Summary: Python client for interacting with PuppetDB
Home-page: http://github.com/arcus-io/puppetdb-python
Author: Arcus, Inc.
Author-email: support@arcus.io
License: Apache 2.0
Download-URL: https://github.com/arcus-io/puppetdb-python/archive/0.0.1.tar.gz
Keywords: puppet,puppetdb
Platform: UNKNOWN
Classifier: Intended Audience :: Developers
Classifier: License :: OSI Approved :: Apache Software License
Classifier: Operating System :: OS Independent
Classifier: Programming Language :: Python
Classifier: Programming Language :: Python :: 2.7
